{
  "circuit_name": "Zandvoort",
  "circuit_number": 26,
  "track_length": 4258,
  "segments": [
    {
      "type": "straight",
      "start_m": 0,
      "end_m": 200,
      "name": "Pit Straight"
    },
    {
      "type": "corner",
      "start_m": 200,
      "end_m": 480,
      "name": "Tarzanbocht",
      "corner_number": 1
    },
    {
      "type": "corner",
      "start_m": 600,
      "end_m": 760,
      "name": "Gerlachbocht",
      "corner_number": 2
    },
    {
      "type": "corner",
      "start_m": 760,
      "end_m": 960,
      "name": "Hugenholtzbocht",
      "corner_number": 3
    },
    {
      "type": "corner",
      "start_m": 1027,
      "end_m": 1140,
      "name": "Hunserug",
      "corner_number": 4
    },
    {
      "type": "corner",
      "start_m": 1150,
      "end_m": 1350,
      "name": "",
      "corner_number": 5
    },
    {
      "type": "corner",
      "start_m": 1350,
      "end_m": 1555,
      "name": "Slotemakerbocht",
      "corner_number": 6
    },
    {
      "type": "corner",
      "start_m": 1555,
      "end_m": 1830,
      "name": "Scheivlak",
      "corner_number": 7
    },
    {
      "type": "corner",
      "start_m": 1920,
      "end_m": 2150,
      "name": "Mastersbocht",
      "corner_number": 8
    },
    {
      "type": "corner",
      "start_m": 2150,
      "end_m": 2350,
      "name": "Bocht 9",
      "corner_number": 9
    },
    {
      "type": "corner",
      "start_m": 2400,
      "end_m": 2650,
      "name": "Bocht 10",
      "corner_number": 10
    },
    {
      "type": "straight",
      "start_m": 2650,
      "end_m": 2990,
      "name": "Back Straight"
    },
    {
      "type": "complex_corner",
      "start_m": 2990,
      "end_m": 3270,
      "name": "Hans Ernst Bocht",
      "corner_numbers": [
        11,
        12
      ]
    },
    {
      "type": "corner",
      "start_m": 3380,
      "end_m": 3600,
      "name": "Kumhobocht",
      "corner_number": 13
    },
    {
      "type": "corner",
      "start_m": 3600,
      "end_m": 3950,
      "name": "Arie Luyendykbocht",
      "corner_number": 14
    },
    {
      "type": "straight",
      "start_m": 3950,
      "end_m": 4258,
      "name": "Pit Straight"
    }
  ],
  "sectors": {
    "s1": 1489,
    "s2": 2967
  }
}